{
  "lessonId": "1",
  "lessonTitle": "Basics1",
  "lessonIcon": "titleIcon1",
  "chapters": [
    {
      "word": "人;男人;女人;男孩;女孩",
      "cardZis":[7],
      "cardCis":[1,2,3,4],
      "cardJus":[1,99],
      "practices": [
        {
          "Q_Type": 0,
          "Q_Service":{"ziCards":[],"ciCards":[],"juCards":[]},
          "Q_Title": "choose a correct picture",
          "Q_Question": "我_*_中国_人",
          "Q_Question_PY":"wo_*_zhong guo_ren",
          "Q_Sound": "人.mp3",
          "Q_Pics": [
            "fish",
            "mother",
            "cat",
            "dog"
          ],
          "Q_Contents": [
            "鱼 / yu",
            "妈妈 / ma ma",
            "猫 / mao",
            "狗 / gou"
          ],
          "Q_Answer": "妈妈 / ma ma"
        }
      ]
    },

    {
      "word": "我;你;她;他们;是",
      "sentence": "Subject+Vebr是+Object;",
      "practices":[
        {
          "Q_Type": 1,
          "Q_Title": "write down the word's translation",
          "Q_Question": "女孩/nv hai",
          "Q_Sound": "女孩.mp3",
          "A_Tips":"Write down the translation",
          "Q_Answer": [
            "girl",
            "unboy",
            "small women"
          ]
        }
      ]
    },{
      "word": "我;你;她;他们;是",
      "sentence": "Subject+Vebr是+Object;",
      "practices":[
        {
          "Q_Type": 0,
          "Q_Service":{"ziCards":[],"ciCards":[],"juCards":[]},
          "Q_Title": "choose a correct picture",
          "Q_Question": "我_*_中国_人",
          "Q_Question_PY":"wo_*_zhong guo_ren",
          "Q_Sound": "人.mp3",
          "Q_Pics": [
            "fish",
            "mother",
            "cat",
            "dog"
          ],
          "Q_Contents": [
            "鱼 / yu",
            "妈妈 / ma ma",
            "猫 / mao",
            "狗 / gou"
          ],
          "Q_Answer": "妈妈 / ma ma"
        }
      ]
    }
  ]
}
